gsea_incontext/__init__.py
gsea_incontext/__main__.py
gsea_incontext/algorithm.py
gsea_incontext/enrichr.py
gsea_incontext/gsea.py
gsea_incontext/gsea_incontext.py
gsea_incontext/parser.py
gsea_incontext/plot.py
gsea_incontext/utils.py
gsea_incontext-0.9.6.dist-info/LICENSE.txt
gsea_incontext-0.9.6.dist-info/METADATA
gsea_incontext-0.9.6.dist-info/WHEEL
gsea_incontext-0.9.6.dist-info/entry_points.txt
gsea_incontext-0.9.6.dist-info/top_level.txt
gsea_incontext-0.9.6.dist-info/RECORD
